{
  "$schema": "http://json-schema.org/schema#", 
  "type": "object", 
  "properties": {
    "rollingUpdate": {
      "description": "Rolling update config params. Present only if type = \"RollingUpdate\".", 
      "$ref": "https://raw.githubusercontent.com/garethr/openshift-json-schema/master/master/_definitions.json#/definitions/v1beta1.RollingUpdateDaemonSet"
    }, 
    "type": {
      "type": "string", 
      "description": "Type of daemon set update. Can be \"RollingUpdate\" or \"OnDelete\". Default is OnDelete."
    }
  }
}