{
  "description": "GitHubWebHookCause has information about a GitHub webhook that triggered a build.",
  "properties": {
    "revision": {
      "description": "revision is the git revision information of the trigger.",
      "$ref": "https://raw.githubusercontent.com/garethr/openshift-json-schema/master/master/_definitions.json#/definitions/com.github.openshift.api.build.v1.SourceRevision"
    },
    "secret": {
      "description": "secret is the obfuscated webhook secret that triggered a build.",
      "type": [
        "string",
        "null"
      ]
    }
  },
  "$schema": "http://json-schema.org/schema#",
  "type": "object"
}