{
  "description": "DeploymentConfigStatus represents the current deployment state.",
  "required": [
    "latestVersion",
    "observedGeneration",
    "replicas",
    "updatedReplicas",
    "availableReplicas",
    "unavailableReplicas"
  ],
  "properties": {
    "availableReplicas": {
      "description": "AvailableReplicas is the total number of available pods targeted by this deployment config.",
      "type": [
        "integer",
        "null"
      ],
      "format": "int32"
    },
    "conditions": {
      "description": "Conditions represents the latest available observations of a deployment config's current state.",
      "type": [
        "array",
        "null"
      ],
      "items": {
        "description": "DeploymentCondition describes the state of a deployment config at a certain point.",
        "required": [
          "type",
          "status"
        ],
        "properties": {
          "lastTransitionTime": {
            "type": [
              "string",
              "null"
            ],
            "format": "date-time"
          },
          "lastUpdateTime": {
            "type": [
              "string",
              "null"
            ],
            "format": "date-time"
          },
          "message": {
            "description": "A human readable message indicating details about the transition.",
            "type": [
              "string",
              "null"
            ]
          },
          "reason": {
            "description": "The reason for the condition's last transition.",
            "type": [
              "string",
              "null"
            ]
          },
          "status": {
            "description": "Status of the condition, one of True, False, Unknown.",
            "type": "string"
          },
          "type": {
            "description": "Type of deployment condition.",
            "type": "string"
          }
        },
        "additionalProperties": false
      },
      "x-kubernetes-patch-merge-key": "type",
      "x-kubernetes-patch-strategy": "merge"
    },
    "details": {
      "description": "DeploymentDetails captures information about the causes of a deployment.",
      "required": [
        "causes"
      ],
      "properties": {
        "causes": {
          "description": "Causes are extended data associated with all the causes for creating a new deployment",
          "type": "array",
          "items": {
            "description": "DeploymentCause captures information about a particular cause of a deployment.",
            "required": [
              "type"
            ],
            "properties": {
              "imageTrigger": {
                "description": "DeploymentCauseImageTrigger represents details about the cause of a deployment originating from an image change trigger",
                "required": [
                  "from"
                ],
                "properties": {
                  "from": {
                    "description": "ObjectReference contains enough information to let you inspect or modify the referred object.",
                    "properties": {
                      "apiVersion": {
                        "description": "API version of the referent.",
                        "type": [
                          "string",
                          "null"
                        ]
                      },
                      "fieldPath": {
                        "description": "If referring to a piece of an object instead of an entire object, this string should contain a valid JSON/Go field access statement, such as desiredState.manifest.containers[2]. For example, if the object reference is to a container within a pod, this would take on a value like: \"spec.containers{name}\" (where \"name\" refers to the name of the container that triggered the event) or if no container name is specified \"spec.containers[2]\" (container with index 2 in this pod). This syntax is chosen only to have some well-defined way of referencing a part of an object.",
                        "type": [
                          "string",
                          "null"
                        ]
                      },
                      "kind": {
                        "description": "Kind of the referent. More info: https://git.k8s.io/community/contributors/devel/api-conventions.md#types-kinds",
                        "type": [
                          "string",
                          "null"
                        ]
                      },
                      "name": {
                        "description": "Name of the referent. More info: https://kubernetes.io/docs/concepts/overview/working-with-objects/names/#names",
                        "type": [
                          "string",
                          "null"
                        ]
                      },
                      "namespace": {
                        "description": "Namespace of the referent. More info: https://kubernetes.io/docs/concepts/overview/working-with-objects/namespaces/",
                        "type": [
                          "string",
                          "null"
                        ]
                      },
                      "resourceVersion": {
                        "description": "Specific resourceVersion to which this reference is made, if any. More info: https://git.k8s.io/community/contributors/devel/api-conventions.md#concurrency-control-and-consistency",
                        "type": [
                          "string",
                          "null"
                        ]
                      },
                      "uid": {
                        "description": "UID of the referent. More info: https://kubernetes.io/docs/concepts/overview/working-with-objects/names/#uids",
                        "type": [
                          "string",
                          "null"
                        ]
                      }
                    },
                    "additionalProperties": false
                  }
                },
                "additionalProperties": false
              },
              "type": {
                "description": "Type of the trigger that resulted in the creation of a new deployment",
                "type": "string"
              }
            },
            "additionalProperties": false
          }
        },
        "message": {
          "description": "Message is the user specified change message, if this deployment was triggered manually by the user",
          "type": [
            "string",
            "null"
          ]
        }
      },
      "additionalProperties": false
    },
    "latestVersion": {
      "description": "LatestVersion is used to determine whether the current deployment associated with a deployment config is out of sync.",
      "type": [
        "integer",
        "null"
      ],
      "format": "int64"
    },
    "observedGeneration": {
      "description": "ObservedGeneration is the most recent generation observed by the deployment config controller.",
      "type": [
        "integer",
        "null"
      ],
      "format": "int64"
    },
    "readyReplicas": {
      "description": "Total number of ready pods targeted by this deployment.",
      "type": [
        "integer",
        "null"
      ],
      "format": "int32"
    },
    "replicas": {
      "description": "Replicas is the total number of pods targeted by this deployment config.",
      "type": [
        "integer",
        "null"
      ],
      "format": "int32"
    },
    "unavailableReplicas": {
      "description": "UnavailableReplicas is the total number of unavailable pods targeted by this deployment config.",
      "type": [
        "integer",
        "null"
      ],
      "format": "int32"
    },
    "updatedReplicas": {
      "description": "UpdatedReplicas is the total number of non-terminated pods targeted by this deployment config that have the desired template spec.",
      "type": [
        "integer",
        "null"
      ],
      "format": "int32"
    }
  },
  "additionalProperties": false,
  "$schema": "http://json-schema.org/schema#",
  "type": "object"
}